metabase_manager/__init__.py
metabase_manager/cli/__init__.py
metabase_manager/cli/main.py
metabase_manager/entities.py
metabase_manager/exceptions.py
metabase_manager/manager.py
metabase_manager/parser.py
metabase_manager/registry.py
metabase_manager-0.2.1.dist-info/entry_points.txt
metabase_manager-0.2.1.dist-info/LICENSE
metabase_manager-0.2.1.dist-info/WHEEL
metabase_manager-0.2.1.dist-info/METADATA
metabase_manager-0.2.1.dist-info/RECORD
